dial_gui/__init__.py
dial_gui/__main__.py
dial_gui/app.py
dial_gui/event_filters/__init__.py
dial_gui/event_filters/panning_event_filter.py
dial_gui/event_filters/resizable_node_event_filter.py
dial_gui/event_filters/zoom_event_filter.py
dial_gui/main_window/__init__.py
dial_gui/main_window/main_menubar.py
dial_gui/main_window/main_window.py
dial_gui/node_editor/__init__.py
dial_gui/node_editor/graphics_connection.py
dial_gui/node_editor/graphics_connection_painter.py
dial_gui/node_editor/graphics_node.py
dial_gui/node_editor/graphics_node_painter.py
dial_gui/node_editor/graphics_port.py
dial_gui/node_editor/graphics_port_painter.py
dial_gui/node_editor/graphics_scene.py
dial_gui/node_editor/graphics_scene_painter.py
dial_gui/node_editor/nodes_windows/__init__.py
dial_gui/node_editor/nodes_windows/node_panel.py
dial_gui/node_editor/nodes_windows/nodes_window.py
dial_gui/node_editor/nodes_windows/nodes_windows_group.py
dial_gui/node_editor/type_colors.py
dial_gui/project/__init__.py
dial_gui/project/project_gui.py
dial_gui/project/project_manager_gui.py
dial_gui/utils/__init__.py
dial_gui/utils/application.py
dial_gui/utils/initialization.py
dial_gui/widgets/__init__.py
dial_gui/widgets/editor_tabwidget/__init__.py
dial_gui/widgets/editor_tabwidget/editor_tabwidget.py
dial_gui/widgets/editor_tabwidget/tab_settings_dialog.py
dial_gui/widgets/log/__init__.py
dial_gui/widgets/log/logger_dialog.py
dial_gui/widgets/log/logger_textbox.py
dial_gui/widgets/menus/__init__.py
dial_gui/widgets/menus/file_menu.py
dial_gui/widgets/menus/nodes_menu.py
dial_gui/widgets/menus/plugins_menu.py
dial_gui/widgets/menus/projects_menu.py
dial_gui/widgets/menus/windows_menu.py
dial_gui/widgets/node_editor/__init__.py
dial_gui/widgets/node_editor/node_editor_view.py
dial_gui/widgets/node_editor/node_editor_view_menu.py
dial_gui/widgets/node_editor/node_editor_window.py
dial_gui/widgets/notebook_editor/__init__.py
dial_gui/widgets/notebook_editor/notebook_editor_dialog.py
dial_gui-0.11a0.dist-info/LICENSE
dial_gui-0.11a0.dist-info/WHEEL
dial_gui-0.11a0.dist-info/METADATA
dial_gui-0.11a0.dist-info/RECORD
