Metadata-Version: 2.1
Name: dial-gui
Version: 0.11a0
Summary: A node-based GUI for Deep Learning tasks
Home-page: https://github.com/dial-app/dial-gui
License: GPL-3.0-only
Author: David Afonso
Author-email: davafons@gmail.com
Requires-Python: >=3.6.0,<=3.8.3
Classifier: License :: OSI Approved :: GNU General Public License v3 (GPLv3)
Classifier: Programming Language :: Python :: 3
Classifier: Programming Language :: Python :: 3.6
Classifier: Programming Language :: Python :: 3.7
Classifier: Programming Language :: Python :: 3.8
Requires-Dist: PySide2 (>=5.12.6,<6.0.0)
Requires-Dist: dependency-injector (>=3.15.6,<4.0.0)
Requires-Dist: dial-core (>=0.21a0)
Requires-Dist: nbconvert (>=5.6.1,<6.0.0)
Requires-Dist: qimage2ndarray (>=1.8.3,<2.0.0)
Project-URL: Repository, https://github.com/dial-app/dial-gui
